fluxloop_mcp/__init__.py
fluxloop_mcp/server.py
fluxloop_mcp/index/__init__.py
fluxloop_mcp/index/embedder.py
fluxloop_mcp/index/ingestor.py
fluxloop_mcp/index/retriever.py
fluxloop_mcp/index/store.py
fluxloop_mcp/index/validator.py
fluxloop_mcp/recipes/__init__.py
fluxloop_mcp/recipes/registry.py
fluxloop_mcp/schemas/runner_pattern_metadata.json
fluxloop_mcp/tests/__init__.py
fluxloop_mcp/tests/fixtures/__init__.py
fluxloop_mcp/tools/__init__.py
fluxloop_mcp/tools/analyze_repository.py
fluxloop_mcp/tools/detect_frameworks.py
fluxloop_mcp/tools/faq.py
fluxloop_mcp/tools/generate_integration_steps.py
fluxloop_mcp/tools/propose_edit_plan.py
fluxloop_mcp/tools/run_integration_workflow.py
fluxloop_mcp/tools/validate_edit_plan.py
fluxloop_mcp-0.1.0.dist-info/METADATA
fluxloop_mcp-0.1.0.dist-info/WHEEL
fluxloop_mcp-0.1.0.dist-info/entry_points.txt
fluxloop_mcp-0.1.0.dist-info/top_level.txt
fluxloop_mcp-0.1.0.dist-info/RECORD
