Metadata-Version: 2.4
Name: fluxloop-mcp
Version: 0.1.0
Summary: Fluxloop MCP server providing repository analysis and documentation tools.
Author-email: Fluxloop Team <team@fluxloop.dev>
License: Apache-2.0
Project-URL: Homepage, https://github.com/chuckgu/fluxloop
Project-URL: Repository, https://github.com/chuckgu/fluxloop
Project-URL: Documentation, https://docs.fluxloop.io/mcp
Classifier: Development Status :: 3 - Alpha
Classifier: Intended Audience :: Developers
Classifier: License :: OSI Approved :: Apache Software License
Classifier: Programming Language :: Python :: 3
Classifier: Programming Language :: Python :: 3.11
Classifier: Programming Language :: Python :: 3.12
Requires-Python: >=3.11
Requires-Dist: msgspec>=0.18.6
Provides-Extra: dev
Requires-Dist: pytest>=7.0.0; extra == "dev"
Requires-Dist: ruff>=0.5.0; extra == "dev"
Requires-Dist: mypy>=1.10.0; extra == "dev"
